simplekv/__init__.py
simplekv/_compat.py
simplekv/cache.py
simplekv/crypt.py
simplekv/decorator.py
simplekv/fs.py
simplekv/gae.py
simplekv/git.py
simplekv/idgen.py
simplekv/contrib/__init__.py
simplekv/db/__init__.py
simplekv/db/mongo.py
simplekv/db/sql.py
simplekv/memory/__init__.py
simplekv/memory/redisstore.py
simplekv/net/__init__.py
simplekv/net/_azurestore_common.py
simplekv/net/_azurestore_new.py
simplekv/net/_azurestore_old.py
simplekv/net/azurestore.py
simplekv/net/botostore.py
simplekv-0.14.0.dist-info/AUTHORS
simplekv-0.14.0.dist-info/LICENSE
simplekv-0.14.0.dist-info/METADATA
simplekv-0.14.0.dist-info/WHEEL
simplekv-0.14.0.dist-info/top_level.txt
simplekv-0.14.0.dist-info/RECORD
