Metadata-Version: 1.1
Name: simplekv
Version: 0.14.0
Summary: A key-value storage for binary data, support many backends.
Home-page: http://github.com/mbr/simplekv
Author: Marc Brinkmann
Author-email: git@marcbrinkmann.de
License: MIT
Platform: UNKNOWN
Classifier: Programming Language :: Python :: 2
Classifier: Programming Language :: Python :: 3
